pysam-0.23.3.dist-info/RECORD
pysam-0.23.3.dist-info/WHEEL
pysam-0.23.3.dist-info/top_level.txt
pysam-0.23.3.dist-info/METADATA
pysam-0.23.3.dist-info/licenses/AUTHORS
pysam-0.23.3.dist-info/licenses/COPYING
pysam/libcsamtools.cpython-310-darwin.so
pysam/libctabixproxies.pyi
pysam/libchtslib.cpython-310-darwin.so
pysam/libcbgzf.cpython-310-darwin.so
pysam/libctabix.cpython-310-darwin.so
pysam/libcbcf.pyi
pysam/libcfaidx.pyx
pysam/libcsamtools.pxd
pysam/libcvcf.cpython-310-darwin.so
pysam/libcbgzf.pxd
pysam/version.h
pysam/bcftools.py
pysam/version.pyi
pysam/libcalignedsegment.pyi
pysam/config.py
pysam/libcbcftools.pyx
pysam/version.py
pysam/libcalignedsegment.cpython-310-darwin.so
pysam/libcsamfile.pyx
pysam/libctabix.pyx
pysam/pysam_stream.h
pysam/libcvcf.pyx
pysam/htslib_util.h
pysam/libcalignmentfile.pyx
pysam/samtools.py
pysam/pysam_util.h
pysam/libchtslib.pyx
pysam/libcalignedsegment.pxd
pysam/libcbgzf.pyi
pysam/libcsamtools.pyi
pysam/libcutils.cpython-310-darwin.so
pysam/libcutils.pyx
pysam/__init__.py
pysam/libcbcf.pxd
pysam/libcsamfile.cpython-310-darwin.so
pysam/libctabixproxies.pxd
pysam/Pileup.py
pysam/libctabixproxies.pyx
pysam/libcfaidx.pyi
pysam/libcbcf.pyx
pysam/libcbcf.cpython-310-darwin.so
pysam/utils.py
pysam/libcutils.pxd
pysam/libcalignmentfile.cpython-310-darwin.so
pysam/libcalignedsegment.pyx
pysam/libcbcftools.cpython-310-darwin.so
pysam/libcbcftools.pyi
pysam/libchtslib.pxd
pysam/libcsamfile.pyi
pysam/libctabix.pyi
pysam/py.typed
pysam/libcvcf.pyi
pysam/libcalignmentfile.pxd
pysam/libcalignmentfile.pyi
pysam/libcvcf.pxd
pysam/libctabix.pxd
pysam/libcsamfile.pxd
pysam/pysam_util.c
pysam/libcbcftools.pxd
pysam/libchtslib.pyi
pysam/csamtools_util.h
pysam/htslib_util.c
pysam/libcbgzf.pyx
pysam/libcfaidx.cpython-310-darwin.so
pysam/conftest_cstd.c
pysam/libcutils.pyi
pysam/libcsamtools.pyx
pysam/cbcftools_util.h
pysam/libctabixproxies.cpython-310-darwin.so
pysam/libcfaidx.pxd
pysam/include/__init__.py
pysam/include/htslib/sam_internal.h
pysam/include/htslib/htslib.mk
pysam/include/htslib/htscodecs_bundled.mk
pysam/include/htslib/faidx.c
pysam/include/htslib/vcfutils.c
