Metadata-Version: 2.1
Name: pysam
Version: 0.23.3
Summary: Package for reading, manipulating, and writing genomic data
Home-page: https://github.com/pysam-developers/pysam
Author: Andreas Heger
Author-email: Andreas Heger <andreas.heger@gmail.com>
License: MIT License
Project-URL: Documentation, https://pysam.readthedocs.io/
Project-URL: Release notes, https://pysam.readthedocs.io/en/stable/release.html
Platform: POSIX
Platform: UNIX
Platform: MacOS
Classifier: Development Status :: 4 - Beta
Classifier: Intended Audience :: Science/Research
Classifier: Intended Audience :: Developers
Classifier: License :: OSI Approved
Classifier: Programming Language :: Python
Classifier: Topic :: Software Development
Classifier: Topic :: Scientific/Engineering
Classifier: Operating System :: POSIX
Classifier: Operating System :: Unix
Classifier: Operating System :: MacOS
Requires-Python: >=3.8
License-File: AUTHORS
